{
  "name": "Barbacoa Beef (Pressure Cooker or Instant Pot)",
  "description": "If you like cumin and spicy food, then you'll love Barbacoa Beef. Spicy shredded beef braised in a blend of chipotle adobo, cumin, cloves, garlic and oregano.",
  "servings": "9 Servings",
  "prep_time": "20m",
  "cook_time": "1h",
  "total_time": "1h 20m",
  "ingredient_sections": [
    {
      "ingredients": [
        {
          "quantity": 5,
          "unit": "each",
          "ingredient": "cloves garlic"
        },
        {
          "quantity": 0.5,
          "unit": "each",
          "ingredient": "medium onion"
        },
        {
          "quantity": 1,
          "unit": "each",
          "ingredient": "lime (juice)"
        },
        {
          "quantity": {
            "min": 2,
            "max": 4
          },
          "unit": "tbsp",
          "ingredient": "canned chipotle in adobo sauce (to taste)"
        },
        {
          "quantity": 1,
          "unit": "tbsp",
          "ingredient": "ground cumin"
        },
        {
          "quantity": 1,
          "unit": "tbsp",
          "ingredient": "ground oregano"
        },
        {
          "quantity": 0.5,
          "unit": "tsp",
          "ingredient": "ground cloves"
        },
        {
          "quantity": 1,
          "unit": "cup",
          "ingredient": "water"
        },
        {
          "quantity": 3,
          "unit": "lb",
          "ingredient": "beef eye of round or bottom round roast (all fat trimmed)"
        },
        {
          "quantity": 2.5,
          "unit": "tsp",
          "ingredient": "kosher salt"
        },
        {
          "quantity": null,
          "unit": null,
          "ingredient": "black pepper"
        },
        {
          "quantity": 1,
          "unit": "tsp",
          "ingredient": "olive oil"
        },
        {
          "quantity": 3,
          "unit": "each",
          "ingredient": "bay leaves"
        }
      ]
    }
  ],
  "step_sections": [
    {
      "steps": [
        "Place garlic, onion, lime juice, cumin, oregano, chipotles, cloves and water in a blender and puree until smooth.",
        "Trim all the fat off meat, cut into 3-inch pieces. Season with 2 teaspoons salt and black pepper. Heat the pressure cooker on high (use saute button for Instant Pot), when hot add the oil and brown the meat, in batches on all side, about 5 minutes. Add the sauce from the blender and bay leaves, cover and cook on high pressure until the meat is tender and easily shreds with 2 forks, about 1 hour. (in my Instant Pot I cooked it 65 minutes). (If you're making this on the stove, simmer it on low at least 4 hours, adding more water as needed to make sure it doesn't dry out.) Natural release.",
        "Once cooked and the meat is tender, remove the meat and place in a dish. Shred with two forks, and reserve the liquid for later (discard the bay leaf). Return the shredded meat to the pot, add 1/2 teaspoon salt or to taste, 1/2 tsp cumin and 1 1/2 cups of the reserved liquid."
      ]
    }
  ],
  "tags": [
    "favorite"
  ]
}
